odoo8_addon_stock_picking_mass_action-8.0.1.0.0-py2.7-nspkg.pth
odoo_addons/stock_picking_mass_action/__openerp__.py
odoo_addons/stock_picking_mass_action/__init__.py
odoo_addons/stock_picking_mass_action/README.rst
odoo_addons/stock_picking_mass_action/models/__init__.py
odoo_addons/stock_picking_mass_action/models/stock_picking.py
odoo_addons/stock_picking_mass_action/i18n/stock_picking_mass_action.pot
odoo_addons/stock_picking_mass_action/i18n/de.po
odoo_addons/stock_picking_mass_action/i18n/fr.po
odoo_addons/stock_picking_mass_action/wizard/mass_action.py
odoo_addons/stock_picking_mass_action/wizard/mass_action_view.xml
odoo_addons/stock_picking_mass_action/wizard/__init__.py
odoo_addons/stock_picking_mass_action/test/test_stock_picking_mass_action.yml
odoo_addons/stock_picking_mass_action/data/ir_cron.xml
odoo8_addon_stock_picking_mass_action-8.0.1.0.0.dist-info/top_level.txt
odoo8_addon_stock_picking_mass_action-8.0.1.0.0.dist-info/WHEEL
odoo8_addon_stock_picking_mass_action-8.0.1.0.0.dist-info/RECORD
odoo8_addon_stock_picking_mass_action-8.0.1.0.0.dist-info/metadata.json
odoo8_addon_stock_picking_mass_action-8.0.1.0.0.dist-info/DESCRIPTION.rst
odoo8_addon_stock_picking_mass_action-8.0.1.0.0.dist-info/METADATA
odoo8_addon_stock_picking_mass_action-8.0.1.0.0.dist-info/namespace_packages.txt
