Metadata-Version: 2.0
Name: odoo8-addon-stock-picking-mass-action
Version: 8.0.1.0.0
Summary: Stock Picking Mass Action
Home-page: https://github.com/OCA/stock-logistics-workflow/
Author: UNKNOWN
Author-email: UNKNOWN
License: AGPL-3
Platform: UNKNOWN
Requires-Dist: odoo (<9.0a,>=8.0a)
Classifier: Programming Language :: Python :: 2.7
Classifier: Framework :: Odoo
Classifier: License :: OSI Approved :: GNU Affero General Public License v3
